{
  "SakikoMod:Config": {
    "TEXT": [
      "语音音量",
      "其他角色启用本Mod专属Boss（暂时没有！）",
      "启用被废弃的卡牌与遗物（重启后生效）",
      "启用爱音Mod卡牌",
      "解锁本Mod进阶20（重启后生效）"
    ],
    "EXTRA_TEXT": [
      "不建议启用，这类卡牌或遗物通常是早期设计且 #y缺少维护 。",
      "谨慎操作，这是 #r不可逆 的。"
    ]
  },
  "SakikoMod:MusicDrawPilePanel": {
    "TEXT": [
      "我的歌单是 #r空的 。"
    ]
  },
  "SakikoMod:MusicDrawPileViewScreen": {
    "TEXT": [
      "每拥有12层 音符 时，从这里抽一张牌。",
      "（这里显示的卡牌按照稀有度排列）",
      "返回",
      "歌单"
    ]
  },
  "SakikoMod:MusicCardType": {
    "TEXT": [
      "音乐"
    ]
  },
  "SakikoMod:MusicCardReward": {
    "TEXT": [
      "将一张音乐牌加入你的牌组中",
      "选择一张音乐牌"
    ]
  },
  "SakikoMod:MusicSlot": {
    "TEXT": [
      "待演奏区",
      "回合开始时，演奏其中的音乐。每拥有两名队友，额外演奏一首。",
      " NL 当前歌单： NL ",
      "当前暂无等待演奏的音乐。",
      "敌方待演奏区",
      "敌方将要演奏的音乐。"
    ]
  },
  "SakikoMod:SelectCard": {
    "TEXT": [
      "抽牌堆",
      "手牌",
      "弃牌堆",
      "消耗堆",
      "歌单"
    ],
    "EXTRA_TEXT": [
      "目标牌堆（%s）是 #r空的 。",
      "目标牌堆 #r未指定 。",
      "选择 %d 张牌",
      "选择任意张牌"
    ]
  },
  "SakikoMod:MoonLightModifier": {
    "TEXT": [
      "%s NL 临时： sakikomod:白月光 ",
      "临时： sakikomod:白月光"
    ]
  },
  "SakikoMod:RememberModifier": {
    "TEXT": [
      "%s NL 临时： sakikomod:破碎的回忆  ",
      "临时： sakikomod:破碎的回忆"
    ]
  },
  "SakikoMod:OptionExhaustModifier": {
    "TEXT": [
      "%s NL 临时： *消耗  ",
      "临时： *消耗"
    ]
  },
  "SakikoMod:ChaosInfo": {
    "TEXT": [
      "黑暗吟游诗人",
      "黑暗之剑",
      "漆黑的玫瑰人生",
      "最强攻击魔法——EXPLOSION",
      "无法超越的破灭——EXPLOSION",
      "崩坏万象——EXPLOSION",
      "不可视境界线",
      "黑翼杰克斯原型Ⅱ"
    ],
    "EXTRA_TEXT": [
      "一切的生命只不过是被困于永恒黑暗中甜蜜的奴隶。",
      "狱炎的黑暗之剑将斩断你的隐形之法！",
      "侵蚀心灵的重力共振...爱之迷宫恋之曲径你与我的魔导书，吾后背初生的羽翼伴随着漆黑的阴翳。血腥的玫瑰人生！",
      "比黑色更黑，比黑暗更暗的漆黑，在此寄讬吾真红的金光吧！",
      "觉醒之时的到来，荒谬教会的堕落章理，成为无形的扭曲而显现吧！",
      "起舞吧，起舞吧，起舞吧！吾之力量本源之愿的崩坏，无人可及的崩坏，将天地万象焚烧殆尽，自深渊降临吧，这就是人类最强威力的攻击手段，这就是究级攻击魔法， Explosion！",
      "爆裂吧，现实！粉碎吧，精神！Banishiment this world！",
      "绽裂吧暗之扉！解放所现黑暗，将终焉的王之力贯彻虚空引路终世！"
    ]
  }
}